django_my_lib/__init__.py
django_my_lib/admin.py
django_my_lib/apps.py
django_my_lib/models.py
django_my_lib/templates/django_my_lib/home.html
django_my_lib/templatetags/__init__.py
django_my_lib/templatetags/sample_tags.py
django_my_lib/urls.py
django_my_lib/views.py
django_my_lib-0.1.6.dist-info/METADATA
django_my_lib-0.1.6.dist-info/WHEEL
django_my_lib-0.1.6.dist-info/licenses/LICENSE
django_my_lib-0.1.6.dist-info/RECORD
