Metadata-Version: 2.4
Name: django-my-lib
Version: 0.1.6
Summary: A handy collection of reusable Django UI components, allowing me to share and integrate elements efficiently across various projects.
License: MIT
License-File: LICENSE
Author: Gustavo Rizzo S M de Albuquerque
Author-email: grizzo.albu@gmail.com
Requires-Python: >=3.14,<4.0
Classifier: License :: OSI Approved :: MIT License
Classifier: Programming Language :: Python :: 3
Classifier: Programming Language :: Python :: 3.14
Requires-Dist: django (>=5.2.7,<6.0.0)
